global_requests/__init__.py
global_requests/migrations/__init__.py
migrations/__init__.py
django_global_requests-1.0.17.dist-info/METADATA
django_global_requests-1.0.17.dist-info/WHEEL
django_global_requests-1.0.17.dist-info/top_level.txt
django_global_requests-1.0.17.dist-info/RECORD
